text2motion_client_api/__init__.py
text2motion_client_api/api_client.py
text2motion_client_api/api_response.py
text2motion_client_api/configuration.py
text2motion_client_api/exceptions.py
text2motion_client_api/py.typed
text2motion_client_api/rest.py
text2motion_client_api/api/__init__.py
text2motion_client_api/api/feedback_api.py
text2motion_client_api/api/generate_api.py
text2motion_client_api/models/__init__.py
text2motion_client_api/models/bone.py
text2motion_client_api/models/feedback_request_body.py
text2motion_client_api/models/generate_request_body.py
text2motion_client_api/models/generate_response_body.py
text2motion_client_api/models/http_validation_error.py
text2motion_client_api/models/location_inner.py
text2motion_client_api/models/skeleton.py
text2motion_client_api/models/validation_error.py
text2motion_client_api-0.1.3.dist-info/METADATA
text2motion_client_api-0.1.3.dist-info/WHEEL
text2motion_client_api-0.1.3.dist-info/top_level.txt
text2motion_client_api-0.1.3.dist-info/RECORD
