Metadata-Version: 2.1
Name: text2motion-client-api
Version: 0.1.3
Summary: OpenAPI generated Python client for Text2Motion API
Home-page: https://github.com/text2motion/python-client
Author: Text2Motion
Author-email: support@text2motion.ai
License: MIT
Keywords: OpenAPI,OpenAPI-Generator,Text2Motion API
Requires-Dist: urllib3<3.0.0,>=1.25.3
Requires-Dist: python-dateutil>=2.8.2
Requires-Dist: pydantic>=2
Requires-Dist: typing-extensions>=4.7.1
